DotsAndBoxes/__init__.py
DotsAndBoxes/__main__.py
DotsAndBoxes/main_window.py
DotsAndBoxes/main_window_controller.py
DotsAndBoxes/dots_and_boxes/__init__.py
DotsAndBoxes/dots_and_boxes/dots_and_boxes.py
DotsAndBoxes/dots_and_boxes/game.py
DotsAndBoxes/dots_and_boxes/model.py
DotsAndBoxes/dots_and_boxes/player.py
DotsAndBoxes/dots_and_boxes/AIPlayer/__init__.py
DotsAndBoxes/dots_and_boxes/AIPlayer/random_AI.py
DotsAndBoxes/dots_and_boxes/AIPlayer/socket_AI.py
DotsAndBoxes-1.1.0.dist-info/DESCRIPTION.rst
DotsAndBoxes-1.1.0.dist-info/METADATA
DotsAndBoxes-1.1.0.dist-info/RECORD
DotsAndBoxes-1.1.0.dist-info/WHEEL
DotsAndBoxes-1.1.0.dist-info/metadata.json
DotsAndBoxes-1.1.0.dist-info/top_level.txt
