Metadata-Version: 2.0
Name: DotsAndBoxes
Version: 1.1.0
Summary: 点格棋对弈软件
Home-page: https://github.com/Everyb0dyLies/Dots-and-Boxes
Author: 高铭
Author-email: gaomingshsf@hotmail.com
License: MIT License
Platform: all
Classifier: Development Status :: 3 - Alpha
Classifier: Natural Language :: Chinese (Simplified)
Classifier: Operating System :: Microsoft :: Windows :: Windows 10
Classifier: Operating System :: POSIX :: Linux
Classifier: Intended Audience :: Developers
Classifier: License :: OSI Approved :: MIT License
Classifier: Programming Language :: Python :: 3
Classifier: Programming Language :: Python :: 3.5
Classifier: Programming Language :: Python :: 3.6
Requires-Dist: PyQt5
